divider.sv
module divider (
  input     clk,      // Clock
  input     rst_n,    // Asynchronous reset active low
  input     data,

  inout [2:0] out
  );
    
  reg [2:0]  clk_cnt;
  reg        overflow;
  reg [2:0]  sum;

  assign out = sum + overflow;

  always_ff @(posedge clk or negedge rst_n) begin
    if(~rst_n) begin
      sum <= 0;
      overflow <= 0;
      clk_cnt <= 1;
    end else begin     
      if(data) begin
        if((out + clk_cnt) == 3'b111) begin
          overflow <= 0;
          sum <= 0;
        end else begin
          {overflow,sum} <= out + clk_cnt; 
        end      
      end
      
      case(clk_cnt)
        1 : clk_cnt <= 2;
        2 : clk_cnt <= 4;
        4 : clk_cnt <= 1;
        default : clk_cnt <= 1;
      endcase
    end
  end
endmodule

top.sv
module top (
  input         clk,    // Clock
  input         rst_n,  // Asynchronous reset active low

  input         data,
  output  [2:0] out
  );

  divider divider0( .clk(clk),
                    .rst_n(rst_n),
                    .data(data),
                    .out(out));
  
endmodule

top_tb.sv
module top_tb;
  reg     clk,rst_n;
  reg     data;
  reg [2:0] out;

    // Clock 
  initial begin
    clk = 0;
    forever #1 clk = ~clk;
  end
  
  top kursach( .clk(clk),
               .rst_n(rst_n),
               .data(data),
               .out(out));
    // Reset
  initial begin
    rst_n  = 1;
               
    #9 rst_n  = 0;
    #1 rst_n  = 1;
    #100 $finish;
  end
  
  // Test0   
  //initial begin
  //  data = 1;
  //end
  
  // Test2
  initial begin 
    #10 data = 1;
    #2 data = 0;
    #2 data = 1;
    #2 data = 0;
    #2 data = 0;
    #2 data = 1;
    #2 data = 0;
    #2 data = 1;
  end
    
  // Dump waves
  initial begin
    $dumpfile("dump.vcd");
    $dumpvars(0, top_tb);
  end
endmodule

dump.vcd
$date
	Tue Oct 28 01:10:12 2014
$end
$version
	ModelSim Version 10.2c
$end
$timescale
	1ns
$end

$scope module top_tb $end
$var reg 1 ! clk $end
$var reg 1 " rst_n $end
$var reg 1 # data $end
$var reg 3 $ out [2:0] $end

$scope module kursach $end
$var wire 1 % clk $end
$var wire 1 & rst_n $end
$var wire 1 ' data $end
$var wire 1 ( out [2] $end
$var wire 1 ) out [1] $end
$var wire 1 * out [0] $end

$scope module divider0 $end
$var wire 1 % clk $end
$var wire 1 & rst_n $end
$var wire 1 ' data $end
$var wire 1 ( out [2] $end
$var wire 1 ) out [1] $end
$var wire 1 * out [0] $end
$var reg 3 + clk_cnt [2:0] $end
$var reg 1 , overflow $end
$var reg 3 - sum [2:0] $end
$upscope $end
$upscope $end
$upscope $end
$enddefinitions $end
#0
$dumpvars
0!
1"
x#
bx $
bx +
x,
bx -
0%
1&
x'
x*
x)
x(
$end
#1
1!
1%
b1 +
#2
0!
0%
#3
1!
1%
b10 +
#4
0!
0%
#5
1!
1%
b100 +
#6
0!
0%
#7
1!
1%
b1 +
#8
0!
0%
#9
0"
1!
0&
1%
b0 -
0,
0*
0)
0(
b0 $
#10
1#
1"
0!
1'
1&
0%
#11
1!
1%
b1 -
b10 +
1*
b1 $
#12
0#
0!
0'
0%
#13
1!
1%
b100 +
#14
1#
0!
1'
0%
#15
1!
1%
b101 -
b1 +
1(
b101 $
#16
0#
0!
0'
0%
#17
1!
1%
b10 +
#18
0!
0%
#19
1!
1%
b100 +
#20
1#
0!
1'
0%
#21
1!
1%
b1 -
1,
b1 +
0*
1)
0(
b10 $
#22
0#
0!
0'
0%
#23
1!
1%
b10 +
#24
1#
0!
1'
0%
#25
1!
1%
b100 -
0,
b100 +
0)
1(
b100 $
#26
0!
0%
#27
1!
1%
b0 -
1,
b1 +
1*
0(
b1 $
#28
0!
0%
#29
1!
1%
b10 -
0,
b10 +
0*
1)
b10 $
#30
0!
0%
#31
1!
1%
b100 -
b100 +
0)
1(
b100 $
#32
0!
0%
#33
1!
1%
b0 -
1,
b1 +
1*
0(
b1 $
#34
0!
0%
#35
1!
1%
b10 -
0,
b10 +
0*
1)
b10 $
#36
0!
0%
#37
1!
1%
b100 -
b100 +
0)
1(
b100 $
#38
0!
0%
#39
1!
1%
b0 -
1,
b1 +
1*
0(
b1 $
#40
0!
0%
#41
1!
1%
b10 -
0,
b10 +
0*
1)
b10 $
#42
0!
0%
#43
1!
1%
b100 -
b100 +
0)
1(
b100 $
#44
0!
0%
#45
1!
1%
b0 -
1,
b1 +
1*
0(
b1 $
#46
0!
0%
#47
1!
1%
b10 -
0,
b10 +
0*
1)
b10 $
#48
0!
0%
#49
1!
1%
b100 -
b100 +
0)
1(
b100 $
#50
0!
0%
#51
1!
1%
b0 -
1,
b1 +
1*
0(
b1 $
#52
0!
0%
#53
1!
1%
b10 -
0,
b10 +
0*
1)
b10 $
#54
0!
0%
#55
1!
1%
b100 -
b100 +
0)
1(
b100 $
#56
0!
0%
#57
1!
1%
b0 -
1,
b1 +
1*
0(
b1 $
#58
0!
0%
#59
1!
1%
b10 -
0,
b10 +
0*
1)
b10 $
#60
0!
0%
#61
1!
1%
b100 -
b100 +
0)
1(
b100 $
#62
0!
0%
#63
1!
1%
b0 -
1,
b1 +
1*
0(
b1 $
#64
0!
0%
#65
1!
1%
b10 -
0,
b10 +
0*
1)
b10 $
#66
0!
0%
#67
1!
1%
b100 -
b100 +
0)
1(
b100 $
#68
0!
0%
#69
1!
1%
b0 -
1,
b1 +
1*
0(
b1 $
#70
0!
0%
#71
1!
1%
b10 -
0,
b10 +
0*
1)
b10 $
#72
0!
0%
#73
1!
1%
b100 -
b100 +
0)
1(
b100 $
#74
0!
0%
#75
1!
1%
b0 -
1,
b1 +
1*
0(
b1 $
#76
0!
0%
#77
1!
1%
b10 -
0,
b10 +
0*
1)
b10 $
#78
0!
0%
#79
1!
1%
b100 -
b100 +
0)
1(
b100 $
#80
0!
0%
#81
1!
1%
b0 -
1,
b1 +
1*
0(
b1 $
#82
0!
0%
#83
1!
1%
b10 -
0,
b10 +
0*
1)
b10 $
#84
0!
0%
#85
1!
1%
b100 -
b100 +
0)
1(
b100 $
#86
0!
0%
#87
1!
1%
b0 -
1,
b1 +
1*
0(
b1 $
#88
0!
0%
#89
1!
1%
b10 -
0,
b10 +
0*
1)
b10 $
#90
0!
0%
#91
1!
1%
b100 -
b100 +
0)
1(
b100 $
#92
0!
0%
#93
1!
1%
b0 -
1,
b1 +
1*
0(
b1 $
#94
0!
0%
#95
1!
1%
b10 -
0,
b10 +
0*
1)
b10 $
#96
0!
0%
#97
1!
1%
b100 -
b100 +
0)
1(
b100 $
#98
0!
0%
#99
1!
1%
b0 -
1,
b1 +
1*
0(
b1 $
